cathay_trade/__init__.py
cathay_trade/account.py
cathay_trade/inventory.py
cathay_trade/login.py
cathay_trade/order.py
cathay_trade/reply.py
cathay_trade/sdk.py
cathay_trade/test.py
cathay_trade/dll/CSAPIComm.dll
cathay_trade/dll/CSTrader.dll
cathay_trade/dll/ICSharpCode.SharpZipLib.dll
cathay_trade/dll/Interop.CGCAPIATLLib.dll
cathay_trade/dll/Interop.FSCAPIATLLib.dll
cathay_trade-1.0.5.dist-info/LICENSE
cathay_trade-1.0.5.dist-info/METADATA
cathay_trade-1.0.5.dist-info/WHEEL
cathay_trade-1.0.5.dist-info/top_level.txt
cathay_trade-1.0.5.dist-info/RECORD
