Metadata-Version: 2.1
Name: cathay-trade
Version: 1.0.5
Summary: call trade function
Author: pei-jan
Author-email: orangepower856@hotmail.com
License-File: LICENSE
Requires-Dist: pythonnet
